src/__init__.py
src/setup.py
src/broker/__init__.py
src/broker/broker.py
src/configuration_store/__init__.py
src/configuration_store/configuration_decoder.py
src/configuration_store/configuration_loader.py
src/configuration_store/configuration_store.py
src/configuration_store/json_configuration_decoder.py
src/data_container/__init__.py
src/data_container/data_container.py
src/election_component/__init__.py
src/election_component/election_component.py
src/election_component/network_election_component.py
src/election_component/tuda_election_component.py
src/logger/__init__.py
src/logger/logger.py
src/network_daemon/__init__.py
src/network_daemon/multicast_network_objects.py
src/network_daemon/tcp_network_objects.py
src/singleton/__init__.py
src/singleton/singleton.py
src/train_unit_data_aggregator/__init__.py
src/train_unit_data_aggregator/amqp_transfer_module.py
src/train_unit_data_aggregator/internal_api.py
src/train_unit_data_aggregator/internal_network_api.py
src/train_unit_data_aggregator/network_train_unit_data_aggregator.py
src/train_unit_data_aggregator/train_unit_data_aggregator.py
src/train_unit_data_aggregator/transfer_module.py
src/virtual_tuda/__init__.py
src/virtual_tuda/virtual_network_tuda.py
src/virtual_tuda/virtual_tuda.py
test/__init__.py
test/test_broker.py
test/test_camera_handler.py
test/test_configuration_store.py
test/test_data_container.py
test/test_election_component.py
test/test_internal_network_API.py
test/test_logger.py
test/test_network_daemons.py
test/test_occupancy_processor.py
test/test_train_unit_data_aggregator.py
test/test_virtual_tuda.py
openspace_train_environment-0.0.3.dist-info/METADATA
openspace_train_environment-0.0.3.dist-info/WHEEL
openspace_train_environment-0.0.3.dist-info/top_level.txt
openspace_train_environment-0.0.3.dist-info/RECORD
