Metadata-Version: 2.1
Name: openspace-train-environment
Version: 0.0.3
Summary: The OpenSpace train environment
Home-page: https://github.ugent.be/OpenSpace-DP/train_env
Author: OpenSpace
License: UNKNOWN
Platform: UNKNOWN
Classifier: Programming Language :: Python :: 3
